{"is_source_file": true, "format": "TypeScript", "description": "This file defines a TypeScript type 'ExperienceItem' and exports a list of experience objects containing details about a professional experience.", "external_files": [], "external_methods": [], "published": ["ExperienceItem", "experience"], "classes": [], "methods": [], "calls": [], "search-terms": ["ExperienceItem", "experience", "experience data", "TypeScript type", "experience list"], "state": 2, "file_id": 30, "knowledge_revision": 99, "git_revision": "9685fefa8fb8939ebc2caeee035d07b69deea53a", "revision_history": [{"67": ""}, {"99": "9685fefa8fb8939ebc2caeee035d07b69deea53a"}], "ctags": [{"_type": "tag", "name": "ExperienceItem", "path": "/home/kavia/workspace/code-generation/akshat-mishra-portfolio-41166/portfolio_frontend/src/data/experience.ts", "pattern": "/^export type ExperienceItem = {$/", "language": "TypeScript", "kind": "alias"}, {"_type": "tag", "name": "experience", "path": "/home/kavia/workspace/code-generation/akshat-mishra-portfolio-41166/portfolio_frontend/src/data/experience.ts", "pattern": "/^export const experience: ExperienceItem[] = [$/", "language": "TypeScript", "kind": "constant"}], "hash": "ce9b32ae8d58aac010d839afe50f9465", "format-version": 4, "code-base-name": "portfolio_frontend", "filename": "portfolio_frontend/src/data/experience.ts"}